genevector/__init__.py
genevector/data.py
genevector/embedding.py
genevector/model.py
genevector-0.2.2.dist-info/LICENSE
genevector-0.2.2.dist-info/METADATA
genevector-0.2.2.dist-info/WHEEL
genevector-0.2.2.dist-info/top_level.txt
genevector-0.2.2.dist-info/RECORD
