Metadata-Version: 2.1
Name: genevector
Version: 0.2.2
Summary: Single Cell GeneVector Library
Author-email: Nicholas Ceglia <nickceglia@gmail.com>
Project-URL: Homepage, https://github.com/nceglia/genevector
Project-URL: Documentation, https://genevector.readthedocs.io
Classifier: Programming Language :: Python :: 3
Classifier: License :: OSI Approved :: MIT License
Classifier: Operating System :: OS Independent
Requires-Python: >=3.7
License-File: LICENSE
Requires-Dist: scipy (==1.9.0)
Requires-Dist: leidenalg (==0.8.10)
Requires-Dist: numpy (==1.22.4)
Requires-Dist: sklearn (==0.0)
Requires-Dist: pandas (==1.5.1)
Requires-Dist: scanpy (==1.9.1)
Requires-Dist: umap-learn (==0.5.3)
Requires-Dist: tqdm (==4.64.1)
Requires-Dist: seaborn (==0.12.1)
Requires-Dist: matplotlib (==3.6.2)
Requires-Dist: scikit-misc (==0.1.4)
